phiplot-0.0.1.dist-info/top_level.txt
phiplot-0.0.1.dist-info/METADATA
phiplot-0.0.1.dist-info/WHEEL
phiplot-0.0.1.dist-info/metadata.json
phiplot-0.0.1.dist-info/DESCRIPTION.rst
phiplot-0.0.1.dist-info/RECORD
phiplot/__init__.py
phiplot/phiplot.py
phiplot/string_formatters.py
