Metadata-Version: 2.0
Name: phiplot
Version: 0.0.1
Summary: Python tools for plotting IIT figures
Home-page: http://github.com/grahamfindlay/phiplot
Author: Graham Findlay
Author-email: UNKNOWN
License: GNU General Public License v3.0
Platform: UNKNOWN
Classifier: Development Status :: 3 - Alpha
Classifier: Intended Audience :: Developers
Classifier: Natural Language :: English
Classifier: License :: OSI Approved :: GNU General Public License v3 or later (GPLv3+)
Classifier: Programming Language :: Python
Classifier: Programming Language :: Python :: 3
Classifier: Topic :: Scientific/Engineering
Requires-Dist: numpy
Requires-Dist: pyphi
